tacklebox/__init__.py
tacklebox/helpers.py
tacklebox/hook_management.py
tacklebox/hooks/__init__.py
tacklebox/hooks/model_tracking.py
tacklebox-1.0.3.dist-info/METADATA
tacklebox-1.0.3.dist-info/WHEEL
tacklebox-1.0.3.dist-info/top_level.txt
tacklebox-1.0.3.dist-info/RECORD
